dedomena/__init__.py
dedomena/apis/__init__.py
dedomena/apis/arxiv.py
dedomena/apis/bdrc.py
dedomena/apis/pubmed.py
dedomena/apis/springer.py
dedomena/apis/twitter.py
dedomena/datasets/__init__.py
dedomena/datasets/autonomio.py
dedomena/datasets/mimic.py
dedomena/datasets/pmlb.py
dedomena/generators/__init__.py
Dedomena-0.3.0.dist-info/LICENSE
Dedomena-0.3.0.dist-info/METADATA
Dedomena-0.3.0.dist-info/WHEEL
Dedomena-0.3.0.dist-info/top_level.txt
Dedomena-0.3.0.dist-info/RECORD
